evalda_pub2/__init__.py
evalda_pub2/base_tasks/reformat_abc.ipynb
evalda_pub2/base_tasks/test.py
evalda_pub2/coref_tasks/abc_utils.py
evalda_pub2/coref_tasks/coref_output/coref_abc.png
evalda_pub2/coref_tasks/coref_output/coref_winobias.png
evalda_pub2/coref_tasks/coref_output/detailed_output_abc_coref.csv
evalda_pub2/coref_tasks/coref_output/detailed_output_coref_wino_xlm.csv
evalda_pub2/coref_tasks/coref_utils_OLD(delete).py
evalda_pub2/coref_tasks/requirements.txt
evalda_pub2/coref_tasks/setup.sh
evalda_pub2/coref_tasks/testing-coref.ipynb
evalda_pub2/coref_tasks/wino_utils.py
evalda_pub2/data/DaWinoBias_anti_stereotyped_evalda.txt
evalda_pub2/data/DaWinoBias_pro_stereotyped_evalda.txt
evalda_pub2/data/abc_fem_sents.txt
evalda_pub2/data/abc_male_sents.txt
evalda_pub2/data/name_aug_csv_files/first_names_2023_men.csv
evalda_pub2/data/name_aug_csv_files/first_names_2023_women.csv
evalda_pub2/data/name_aug_csv_files/last_names_2023.csv
evalda_pub2/data/name_aug_csv_files/overlapping_names.csv
evalda_pub2/data/name_aug_csv_files/unisex_names.csv
evalda_pub2/evalda_pub2.py
evalda_pub2/lm_tasks/abc_utils.py
evalda_pub2/lm_tasks/lm_output/fillmask-danish-bert-boxto.png
evalda_pub2/lm_tasks/lm_output/fillmask-xlm-roberta-base.png
evalda_pub2/lm_tasks/lm_output/fillmask_nb-bert-base.png
evalda_pub2/lm_tasks/lm_output/fillmask_nb-bert.csv
evalda_pub2/lm_tasks/lm_output/fillmask_xlm.csv
evalda_pub2/lm_tasks/lm_output/lm_abc_danish-bert-botxo.png
evalda_pub2/lm_tasks/lm_output/lm_abc_danish-bert-botxo_detailed.csv
evalda_pub2/lm_tasks/lm_output/lm_abc_danish-bert-botxo_simple.csv
evalda_pub2/lm_tasks/lm_output/lm_abc_nb-bert-base_detailed.csv
evalda_pub2/lm_tasks/lm_output/lm_abc_nb-bert-base_simple.csv
evalda_pub2/lm_tasks/lm_output/lm_abc_xlm-base.png
evalda_pub2/lm_tasks/lm_output/lm_abc_xlm-base_detailed.csv
evalda_pub2/lm_tasks/lm_output/lm_abc_xlm-base_simple.csv
evalda_pub2/lm_tasks/lm_output/lm_abc_xlm-large.png
evalda_pub2-0.0.7.dist-info/LICENSE
evalda_pub2-0.0.7.dist-info/METADATA
evalda_pub2-0.0.7.dist-info/WHEEL
evalda_pub2-0.0.7.dist-info/RECORD
